success compiling learn.lua
; source chunk: learn.lua
; x86 standard (32-bit, little endian, doubles)

; function [0] definition (level 1) 0
; 0 upvalues, 0 params, is_vararg = 2, 5 stacks
.function  0 0 2 5
.local  "a"  ; 0
.local  "b"  ; 1
.local  "c"  ; 2
.local  "d"  ; 3
.local  "e"  ; 4
.const  100  ; 0
[1] loadk      0   0        ; R0 := 100
[2] vararg     1   5        ; R1 to R4 := ...
[3] return     0   1        ; return 
; end of function 0

; source chunk: luac.out
; x86 standard (32-bit, little endian, doubles)

; function [0] definition (level 1) 0
; 0 upvalues, 0 params, is_vararg = 2, 5 stacks
.function  0 0 2 5
.local  "a"  ; 0
.local  "b"  ; 1
.local  "c"  ; 2
.local  "d"  ; 3
.local  "e"  ; 4
.const  100  ; 0
[1] loadk      0   0        ; R0 := 100
[2] vararg     1   5        ; R1 to R4 := ...
[3] return     0   1        ; return 
; end of function 0

